LICENCE-2.0
MANIFEST.in
README.md
requirements.txt
setup.py
androguard/__init__.py
androguard/misc.py
androguard/session.py
androguard/util.py
androguard/cli/__init__.py
androguard/cli/entry_points.py
androguard/cli/main.py
androguard/core/__init__.py
androguard/core/androconf.py
androguard/core/bytecode.py
androguard/core/mutf8.py
androguard/core/analysis/__init__.py
androguard/core/analysis/analysis.py
androguard/core/analysis/auto.py
androguard/core/analysis/tags.py
androguard/core/api_specific_resources/__init__.py
androguard/core/api_specific_resources/aosp_permissions/permissions_10.json
androguard/core/api_specific_resources/aosp_permissions/permissions_13.json
androguard/core/api_specific_resources/aosp_permissions/permissions_14.json
androguard/core/api_specific_resources/aosp_permissions/permissions_15.json
androguard/core/api_specific_resources/aosp_permissions/permissions_16.json
androguard/core/api_specific_resources/aosp_permissions/permissions_17.json
androguard/core/api_specific_resources/aosp_permissions/permissions_18.json
androguard/core/api_specific_resources/aosp_permissions/permissions_19.json
androguard/core/api_specific_resources/aosp_permissions/permissions_21.json
androguard/core/api_specific_resources/aosp_permissions/permissions_22.json
androguard/core/api_specific_resources/aosp_permissions/permissions_23.json
androguard/core/api_specific_resources/aosp_permissions/permissions_24.json
androguard/core/api_specific_resources/aosp_permissions/permissions_25.json
androguard/core/api_specific_resources/aosp_permissions/permissions_26.json
androguard/core/api_specific_resources/aosp_permissions/permissions_27.json
androguard/core/api_specific_resources/aosp_permissions/permissions_28.json
androguard/core/api_specific_resources/aosp_permissions/permissions_29.json
androguard/core/api_specific_resources/aosp_permissions/permissions_4.json
androguard/core/api_specific_resources/aosp_permissions/permissions_5.json
androguard_en.egg-info/PKG-INFO
androguard_en.egg-info/SOURCES.txt
androguard_en.egg-info/dependency_links.txt
androguard_en.egg-info/entry_points.txt
androguard_en.egg-info/requires.txt
androguard_en.egg-info/top_level.txt