Metadata-Version: 2.1
Name: androguard-en
Version: 3.4.3
Summary: Androguard is a full python tool to play with Android files.
Home-page: https://github.com/androguard/androguard
License: Apache Licence, Version 2.0
Download-URL: https://github.com/androguard/androguard/releases
Platform: UNKNOWN
Classifier: License :: OSI Approved :: Apache Software License
Classifier: Programming Language :: Python
Classifier: Programming Language :: Python :: 3
Classifier: Programming Language :: Python :: 3.6
Classifier: Programming Language :: Python :: 3.7
Classifier: Programming Language :: Python :: 3.8
Classifier: Programming Language :: Python :: 3 :: Only
Classifier: Topic :: Security
Classifier: Topic :: Software Development
Classifier: Topic :: Utilities
Requires-Python: >=3.6
Provides-Extra: GUI
Provides-Extra: magic
Provides-Extra: docs
Provides-Extra: tests
License-File: LICENCE-2.0
